_somoclu_wrap.pyd
somoclu/__init__.py
somoclu/somoclu_wrap.py
somoclu/train.py
somoclu-1.7.5.dist-info/DESCRIPTION.rst
somoclu-1.7.5.dist-info/METADATA
somoclu-1.7.5.dist-info/RECORD
somoclu-1.7.5.dist-info/WHEEL
somoclu-1.7.5.dist-info/metadata.json
somoclu-1.7.5.dist-info/top_level.txt
