Metadata-Version: 2.0
Name: somoclu
Version: 1.7.5
Summary: Massively parallel implementation of self-organizing maps
Home-page: https://somoclu.readthedocs.io/
Author: shichaogao
Author-email: xgdgsc@gmail.com
License: GPL3
Platform: unix
Platform: windows
Classifier: License :: OSI Approved :: GNU General Public License v3 (GPLv3)
Classifier: Operating System :: OS Independent
Classifier: Development Status :: 5 - Production/Stable
Classifier: Topic :: Scientific/Engineering :: Artificial Intelligence
Classifier: Topic :: Scientific/Engineering :: Visualization
Classifier: Intended Audience :: Science/Research
Classifier: Programming Language :: Python
Classifier: Programming Language :: C++
Requires-Dist: matplotlib
Requires-Dist: numpy
Requires-Dist: scipy
